zenith/__init__.py
zenith/__main__.py
zenith/base.py
zenith/cli.py
mukulwaval_zenith-0.0.4.dist-info/LICENSE
mukulwaval_zenith-0.0.4.dist-info/METADATA
mukulwaval_zenith-0.0.4.dist-info/WHEEL
mukulwaval_zenith-0.0.4.dist-info/entry_points.txt
mukulwaval_zenith-0.0.4.dist-info/top_level.txt
mukulwaval_zenith-0.0.4.dist-info/RECORD
