Metadata-Version: 2.1
Name: mukulwaval-zenith
Version: 0.0.4
Summary: Awesome zenith created by MukulWaval
Home-page: https://github.com/MukulWaval/zenith/
Author: MukulWaval
License: UNKNOWN
Platform: UNKNOWN
License-File: LICENSE
Provides-Extra: test
Requires-Dist: black; extra == "test"
Requires-Dist: coverage; extra == "test"
Requires-Dist: flake8; extra == "test"
Requires-Dist: gitchangelog; extra == "test"
Requires-Dist: isort; extra == "test"
Requires-Dist: mkdocs; extra == "test"
Requires-Dist: mypy; extra == "test"
Requires-Dist: pytest; extra == "test"
Requires-Dist: pytest-cov; extra == "test"
